tests/__init__.py
tests/test_cityscapes.py
tests/test_cocostore.py
tests/test_imagenetstore.py
tests/test_imstore.py
torchdatasetutil/__init__.py
torchdatasetutil/__main__.py
torchdatasetutil/build.yaml
torchdatasetutil/cifar10store.py
torchdatasetutil/cityscapesstore.py
torchdatasetutil/cocostore.py
torchdatasetutil/getcityscapes.py
torchdatasetutil/getcoco.py
torchdatasetutil/getsceneflow.py
torchdatasetutil/imagenetstore.py
torchdatasetutil/imstore.py
torchdatasetutil/mixuptransforms.py
torchdatasetutil/sampler.py
torchdatasetutil/version.py
torchdatasetutil-0.1.30.dist-info/LICENSE
torchdatasetutil-0.1.30.dist-info/METADATA
torchdatasetutil-0.1.30.dist-info/WHEEL
torchdatasetutil-0.1.30.dist-info/top_level.txt
torchdatasetutil-0.1.30.dist-info/RECORD
