Metadata-Version: 2.1
Name: torchdatasetutil
Version: 0.1.30
Summary: Utilities to load and use pytorch datasets stored in Minio S3
Home-page: https://github.com/bhlarson/torchdatasetutil
Author: Brad Larson
Author-email: <bhlarson@gmail.com>
License: UNKNOWN
Keywords: python,Machine Learning,Utilities
Platform: UNKNOWN
Classifier: Development Status :: 1 - Planning
Classifier: Intended Audience :: Developers
Classifier: License :: OSI Approved :: Apache Software License
Classifier: Programming Language :: Python :: 3
Classifier: Operating System :: POSIX :: Linux
License-File: LICENSE
Requires-Dist: pyyaml
Requires-Dist: prettytable
Requires-Dist: minio
Requires-Dist: numpy
Requires-Dist: opencv-python
Requires-Dist: torch
Requires-Dist: scikit-learn
